agent_link/__init__.py
agent_link/client.py
agent_link/config.py
agent_link/decorators.py
agent_link/node.py
tests/__init__.py
tests/conftest.py
tests/integration/__init__.py
tests/integration/test_mqtt_connection.py
tests/integration/test_smolagent_integration.py
tests/unit/__init__.py
tests/unit/test_client.py
tests/unit/test_config.py
tests/unit/test_decorators.py
tests/unit/test_node.py
ai_agent_link-0.1.0.dist-info/LICENSE
ai_agent_link-0.1.0.dist-info/METADATA
ai_agent_link-0.1.0.dist-info/WHEEL
ai_agent_link-0.1.0.dist-info/top_level.txt
ai_agent_link-0.1.0.dist-info/RECORD
