Metadata-Version: 2.2
Name: ai-agent-link
Version: 0.1.0
Summary: AI Agent Communication Library
Home-page: https://github.com/jozsefszalma/agent_link
Author: Jozsef Szalma
Author-email: agent_link@szalma.biz
Project-URL: Bug Tracker, https://github.com/jozsefszalma/agent_link/issues
Keywords: distributed,ai,agents,communication,mqtt
Classifier: Programming Language :: Python :: 3
Classifier: Programming Language :: Python :: 3.10
Classifier: Programming Language :: Python :: 3.11
Classifier: Programming Language :: Python :: 3.12
Classifier: License :: OSI Approved :: Apache Software License
Classifier: Operating System :: OS Independent
Classifier: Intended Audience :: Developers
Classifier: Topic :: Communications
Classifier: Topic :: Scientific/Engineering :: Artificial Intelligence
Classifier: Topic :: Software Development :: Libraries
Requires-Python: >=3.10
License-File: LICENSE
Requires-Dist: paho-mqtt>=2.1.0
Requires-Dist: typing-extensions>=4.10.0
Requires-Dist: python-dotenv>=1.0.0
Requires-Dist: smolagents>=0.1.0
